multilink/__init__.py
multilink-0.0.1.dist-info/METADATA
multilink-0.0.1.dist-info/WHEEL
multilink-0.0.1.dist-info/top_level.txt
multilink-0.0.1.dist-info/RECORD
