Metadata-Version: 2.1
Name: multilink
Version: 0.0.1
Summary: UNKNOWN
Home-page: UNKNOWN
Author: 
Author-email: 
License: MIT
Platform: UNKNOWN
